bin/spwrmap
bin/spwrmap_speedtest
include/spw_rmap/crc.hh
include/spw_rmap/error_code.hh
include/spw_rmap/packet_builder.hh
include/spw_rmap/packet_parser.hh
include/spw_rmap/rmap_packet_type.hh
include/spw_rmap/spw_rmap_node_base.hh
include/spw_rmap/spw_rmap_tcp_node.hh
include/spw_rmap/target_node.hh
include/spw_rmap/transaction_database.hh
include/spw_rmap/internal/debug.hh
include/spw_rmap/internal/profiler.hh
include/spw_rmap/internal/spw_rmap_tcp_node_impl.hh
include/spw_rmap/internal/tcp_client.hh
include/spw_rmap/internal/tcp_server.hh
lib/libspw_rmap.a
lib/cmake/spw_rmap/spw_rmapConfig.cmake
lib/cmake/spw_rmap/spw_rmapConfigVersion.cmake
lib/cmake/spw_rmap/spw_rmapTargets-release.cmake
lib/cmake/spw_rmap/spw_rmapTargets.cmake
pyspw_rmap/__init__.py
pyspw_rmap/_cli.py
pyspw_rmap/_core.cpython-311-aarch64-linux-gnu.so
pyspw_rmap/_core.pyi
pyspw_rmap/bin/spwrmap
pyspw_rmap/bin/spwrmap_speedtest
pyspw_rmap-0.3.0.dist-info/METADATA
pyspw_rmap-0.3.0.dist-info/WHEEL
pyspw_rmap-0.3.0.dist-info/entry_points.txt
pyspw_rmap-0.3.0.dist-info/RECORD
pyspw_rmap-0.3.0.dist-info/licenses/LICENSE
